spartera_api_python_sdk-1.0.77.dist-info/licenses/LICENSE
spartera_api_sdk/__init__.py
spartera_api_sdk/api_client.py
spartera_api_sdk/api_response.py
spartera_api_sdk/configuration.py
spartera_api_sdk/exceptions.py
spartera_api_sdk/py.typed
spartera_api_sdk/rest.py
spartera_api_sdk/api/__init__.py
spartera_api_sdk/api/alerts_api.py
spartera_api_sdk/api/api_keys_api.py
spartera_api_sdk/api/asset_price_history_api.py
spartera_api_sdk/api/assets_api.py
spartera_api_sdk/api/cloud_providers_api.py
spartera_api_sdk/api/companies_api.py
spartera_api_sdk/api/connections_api.py
spartera_api_sdk/api/favorites_api.py
spartera_api_sdk/api/job_functions_api.py
spartera_api_sdk/api/storage_engines_api.py
spartera_api_sdk/api/users_api.py
spartera_api_sdk/models/__init__.py
spartera_api_sdk/models/alerts.py
spartera_api_sdk/models/alerts_input.py
spartera_api_sdk/models/alerts_update.py
spartera_api_sdk/models/analyze_company_handle_assets_asset_slug_get200_response.py
spartera_api_sdk/models/api_keys.py
spartera_api_sdk/models/api_keys_input.py
spartera_api_sdk/models/api_keys_update.py
spartera_api_sdk/models/asset_price_history.py
spartera_api_sdk/models/asset_price_history_input.py
spartera_api_sdk/models/asset_price_history_update.py
spartera_api_sdk/models/assets.py
spartera_api_sdk/models/assets_input.py
spartera_api_sdk/models/assets_update.py
spartera_api_sdk/models/cloud_providers.py
spartera_api_sdk/models/cloud_providers_get200_response.py
spartera_api_sdk/models/cloud_providers_input.py
spartera_api_sdk/models/cloud_providers_provider_id_get200_response.py
spartera_api_sdk/models/cloud_providers_provider_id_storage_engines_get200_response.py
spartera_api_sdk/models/cloud_providers_update.py
spartera_api_sdk/models/companies.py
spartera_api_sdk/models/companies_company_id_analytics_assets_get200_response.py
spartera_api_sdk/models/companies_company_id_api_keys_api_key_id_delete200_response.py
spartera_api_sdk/models/companies_company_id_api_keys_api_key_id_delete200_response_data.py
spartera_api_python_sdk-1.0.77.dist-info/METADATA
spartera_api_python_sdk-1.0.77.dist-info/WHEEL
spartera_api_python_sdk-1.0.77.dist-info/top_level.txt
spartera_api_python_sdk-1.0.77.dist-info/RECORD
