Metadata-Version: 2.4
Name: spartera-api-python-sdk
Version: 1.0.77
Summary: Official Python SDK for the Spartera API platform
Home-page: https://github.com/spartera-com/spartera-api-sdks/tree/main/python
Author: API Support
Author-email: support@spartera.com
License: Apache 2.0
Keywords: OpenAPI,OpenAPI-Generator,Spartera API Documentation
License-File: LICENSE
Requires-Dist: urllib3<3.0.0,>=2.1.0
Requires-Dist: python-dateutil>=2.8.2
Requires-Dist: pydantic>=2
Requires-Dist: typing-extensions>=4.7.1
Dynamic: author
Dynamic: author-email
Dynamic: description
Dynamic: description-content-type
Dynamic: home-page
Dynamic: keywords
Dynamic: license
Dynamic: license-file
Dynamic: requires-dist
Dynamic: summary
